{"forwarding_auto_reconnect":false,"custom_size":false,"delete_time":0,"secret_key_id":"","user_name":"yanfauser","remote_port_forwarding":{},"conection_type":100,"sort_time":0,"description":"","proxy_id":"0","authentication_type":1,"drivestoredirect":true,"delete_key_sequence":0,"password":"b2cxSDUzEWRAavNyKtY90qQ+mc2BYRbvnWNGQavX+hJd3hHDIi2c3A==","modified_time":1667038730415,"host":"10.130.40.64","accelerate":false,"id":"g6tphb9qud3nzmxu","height":0,"order":0,"create_time":1667038730415,"port_forwarding_list":[],"parent_update_time":0,"rename_time":0,"backspace_key_sequence":2,"fullscreen":false,"port":22,"terminal_encoding":"UTF-8","parent_id":"2uz5tav2n8vecpu2","exec_channel_enable":true,"width":0,"name":"10.130.40.64","access_time":1671085740635}