{"forwarding_auto_reconnect":false,"custom_size":false,"delete_time":0,"secret_key_id":"","user_name":"root","remote_port_forwarding":{},"conection_type":100,"sort_time":0,"description":"","proxy_id":"0","authentication_type":1,"drivestoredirect":true,"delete_key_sequence":0,"password":"JRYXT1UsWxXRzahqdNFhWR5zzvibceDxVJCAhGqVs0CbC9N2e2z9fA==","modified_time":1671160708925,"host":"116.196.102.177","accelerate":false,"id":"hpxxombhvs06phap","height":0,"order":0,"create_time":1671160708925,"port_forwarding_list":[],"parent_update_time":0,"rename_time":0,"backspace_key_sequence":2,"fullscreen":false,"port":22,"terminal_encoding":"UTF-8","parent_id":"bzdeb7omcmspqgcg","exec_channel_enable":true,"width":0,"name":"116.196.102.177","access_time":1681264145464}